CCAugmentation/__init__.py
CCAugmentation/loaders.py
CCAugmentation/operations.py
CCAugmentation/outputs.py
CCAugmentation/pipelines.py
CCAugmentation/transformations.py
CCAugmentation/examples/__init__.py
CCAugmentation/examples/loading.py
CCAugmentation/examples/pytorch.py
ccaugmentation-0.1.0.dist-info/LICENSE
ccaugmentation-0.1.0.dist-info/METADATA
ccaugmentation-0.1.0.dist-info/WHEEL
ccaugmentation-0.1.0.dist-info/top_level.txt
ccaugmentation-0.1.0.dist-info/RECORD
