Metadata-Version: 2.1
Name: ccaugmentation
Version: 0.1.0
Summary: Data preprocessing & augmentation framework, designed for working with crowd counting datasets and ML/DL framework-independent. Supports multitude of simple as well as advanced transformations, outputs and loaders, all of them to be combined using pipelines.
Home-page: https://github.com/pijuszczyk/CCAugmentation
Author: Piotr Juszczyk
Author-email: piotr.a.juszczyk@gmail.com
License: MIT
Platform: UNKNOWN
Classifier: License :: OSI Approved :: MIT License
Classifier: Programming Language :: Python :: 3
Classifier: Programming Language :: Python :: 3.8
Requires-Dist: numpy (==1.19.3)
Requires-Dist: opencv-python
Requires-Dist: matplotlib
Requires-Dist: scipy
Requires-Dist: tqdm
